<?xml version="1.0" encoding="utf-8"?>
<ArrayOfAbilityData xmlns:xsd="http://www.w3.org/2001/XMLSchema" xmlns:xsi="http://www.w3.org/2001/XMLSchema-instance">
  <AbilityData ID="Bump" Uses="5" Price="0" Shop="true">
    <Description>+1</Description>
    <Slots>
      <Any />
    </Slots>
    <Effects>
      <Give Bonus="1" DiceMult="1" UsesCumulativeBonus="false" TargetsUser="true" />
    </Effects>
  </AbilityData>
  <AbilityData ID="On 6" Uses="0" Price="0">
    <Description>On 6, does 10</Description>
    <Slots>
      <Equals Value="6" />
    </Slots>
    <Effects>
      <Damage Bonus="10" UsesCumulativeBonus="false" TargetsUser="false" />
    </Effects>
  </AbilityData>
  <AbilityData ID="Poke" Uses="3" EqualDice="true" Price="0">
    <Description>Pokes for 1 _++</Description>
    <Slots>
      <Equals Value="1" />
    </Slots>
    <Effects>
      <Damage Bonus="1" UsesCumulativeBonus="false" TargetsUser="false" />
    </Effects>
  </AbilityData>
  <AbilityData ID="Reroll" Uses="3" Price="0" Shop="true">
    <Description>Reroll dice</Description>
    <Slots>
      <Any />
    </Slots>
    <Effects>
      <Roll Bonus="1" UsesCumulativeBonus="false" TargetsUser="true" />
    </Effects>
  </AbilityData>
  <AbilityData ID="Aphrodisiac" Uses="0" Price="0">
    <Description>Throw it for 6 Arousal</Description>
    <Slots>
      <Equals Value="6" />
    </Slots>
    <Effects>
      <Damage Bonus="6" UsesCumulativeBonus="false" TargetsUser="false" />
    </Effects>
  </AbilityData>
  <AbilityData ID="Dice potion" Uses="0" Price="0">
    <Description>Create 2 _Die from thin air.</Description>
    <Slots>
      <Equals Value="2" />
    </Slots>
    <Effects>
      <Roll Bonus="2" UsesCumulativeBonus="false" TargetsUser="true" />
    </Effects>
  </AbilityData>
  <AbilityData ID="Fire Potion" Uses="0" Price="0">
    <Description>Make them fall in love for 5 _Aro</Description>
    <Slots>
      <Equals Value="5" />
    </Slots>
    <Effects>
      <Trait Bonus="5" UsesCumulativeBonus="false" TargetsUser="false" Trait="Aroused" />
    </Effects>
  </AbilityData>
  <AbilityData ID="Slime" Uses="0" Price="0">
    <Description>Is it really a potion? 4 _Sti</Description>
    <Slots>
      <Equals Value="4" />
    </Slots>
    <Effects>
      <Trait Bonus="4" UsesCumulativeBonus="false" TargetsUser="false" Trait="Sticky" />
    </Effects>
  </AbilityData>
  <AbilityData ID="Frost Potion" Uses="0" Price="0">
    <Description>Freeze yourself for 2 _Fre</Description>
    <Slots>
      <Equals Value="1" />
    </Slots>
    <Effects>
      <Trait Bonus="2" UsesCumulativeBonus="false" TargetsUser="true" Trait="Unfeeling" />
    </Effects>
  </AbilityData>
  <AbilityData ID="Tangle sack" Uses="0" Price="0">
    <Description>Immobilise your opponent and give them 3 _Bon</Description>
    <Slots>
      <Equals Value="3" />
    </Slots>
    <Effects>
      <Trait Bonus="3" UsesCumulativeBonus="false" TargetsUser="false" Trait="Bondage" />
    </Effects>
  </AbilityData>
  <AbilityData ID="Vines" Uses="0" Price="5">
    <Description>Tie them up for _Die and 1 Bondage</Description>
    <Slots>
      <EvenOdd isEven="true" />
    </Slots>
    <Effects>
      <Damage Bonus="0" DiceMult="1" UsesCumulativeBonus="false" TargetsUser="false" />
      <Trait Bonus="1" UsesCumulativeBonus="false" TargetsUser="false" Trait="Bondage" />
    </Effects>
  </AbilityData>
  <AbilityData ID="Pollen" Uses="0" Price="5">
    <Description>Envelop yourself in pollen and gain 3 _Phe</Description>
    <Slots>
      <EvenOdd isEven="false" />
    </Slots>
    <Effects>
      <Trait Bonus="3" UsesCumulativeBonus="false" TargetsUser="true" Trait="Pheromones" />
    </Effects>
  </AbilityData>
  <AbilityData ID="Lust Spell" Uses="0" Price="5">
    <Description>Arouse for _Die/2 and gives 2 _Aro</Description>
    <Slots>
      <EvenOdd isEven="false" />
    </Slots>
    <Effects>
      <Damage Bonus="0" DiceMult="0.5" UsesCumulativeBonus="false" TargetsUser="false" />
      <Trait Bonus="2" UsesCumulativeBonus="false" TargetsUser="false" Trait="Aroused" />
    </Effects>
  </AbilityData>
  <AbilityData ID="Chastity Belt" Uses="0" Price="5">
    <Description>Give _Die _Cha</Description>
    <Slots>
      <Any />
    </Slots>
    <Effects>
      <Trait Bonus="0" DiceMult="1" UsesCumulativeBonus="false" TargetsUser="false" Trait="Chastity" />
    </Effects>
  </AbilityData>
  <AbilityData ID="Seductive dance" Uses="2" Price="0">
    <Description>Dance for 2 + _++, increased each use</Description>
    <Slots>
      <EvenOdd isEven="false" />
    </Slots>
    <Effects>
      <Damage Bonus="2" UsesCumulativeBonus="true" TargetsUser="false" />
    </Effects>
  </AbilityData>
  <AbilityData ID="Handjob" Uses="0" Price="0">
    <Description>Stroke for _Die</Description>
    <Slots>
      <Any />
    </Slots>
    <Effects>
      <Damage Bonus="0" DiceMult="1" UsesCumulativeBonus="false" TargetsUser="false" />
    </Effects>
  </AbilityData>
  <AbilityData ID="Holy Light" Uses="0" Price="5">
    <Description>Inflicts _Die and 2 _Aro</Description>
    <Slots>
      <EvenOdd isEven="false" />
    </Slots>
    <Effects>
      <Damage Bonus="0" DiceMult="1" UsesCumulativeBonus="false" TargetsUser="false" />
      <Trait Bonus="2" UsesCumulativeBonus="false" TargetsUser="false" Trait="Aroused" />
    </Effects>
  </AbilityData>
  <AbilityData ID="Holy Water" Uses="0" Price="5">
    <Description>Sprays Holy Water and 2 _Sti</Description>
    <Slots>
      <Equals Value="1" />
    </Slots>
    <Effects>
      <Trait Bonus="2" UsesCumulativeBonus="false" TargetsUser="false" Trait="Sticky" />
    </Effects>
  </AbilityData>
  <AbilityData ID="Pray" Uses="0" Price="5">
    <Description>Submit for _Die _Sub</Description>
    <Slots>
      <EvenOdd isEven="true" />
    </Slots>
    <Effects>
      <Trait Bonus="0" DiceMult="1" UsesCumulativeBonus="false" TargetsUser="true" Trait="Sub" />
    </Effects>
  </AbilityData>
  <AbilityData ID="Big Guns" Uses="0" Total="15" Price="5">
    <Description>Gives 10 Arousal</Description>
    <Slots>
      <Any />
    </Slots>
    <Effects>
      <Damage Bonus="10" UsesCumulativeBonus="false" TargetsUser="false" />
    </Effects>
  </AbilityData>
  <AbilityData ID="Reverence" Uses="0" Price="0">
    <Description>Show your inferiority and gain _Die _Sub</Description>
    <Slots>
      <MinMax Value="3" IsMax="true" />
    </Slots>
    <Effects>
      <Trait Bonus="0" DiceMult="1" UsesCumulativeBonus="false" TargetsUser="true" Trait="Sub" />
    </Effects>
  </AbilityData>
  <AbilityData ID="Calm Down" Uses="0" Price="2">
    <Description>Lower _Die by one</Description>
    <Slots>
      <MinMax Value="2" IsMax="false" />
    </Slots>
    <Effects>
      <Give Bonus="-1" DiceMult="1" UsesCumulativeBonus="false" TargetsUser="true" />
    </Effects>
  </AbilityData>
  <AbilityData ID="Exitement" Uses="0" Price="2">
    <Description>Increase the _Die by one</Description>
    <Slots>
      <MinMax Value="5" IsMax="true" />
    </Slots>
    <Effects>
      <Give Bonus="1" DiceMult="1" UsesCumulativeBonus="false" TargetsUser="true" />
    </Effects>
  </AbilityData>
  <AbilityData ID="Retry" Uses="0" Price="2">
    <Description>Roll again</Description>
    <Slots>
      <Any />
    </Slots>
    <Effects>
      <Roll Bonus="1" UsesCumulativeBonus="false" TargetsUser="true" />
    </Effects>
  </AbilityData>
  <AbilityData ID="Split" Uses="0" Price="2">
    <Description>Split _Die into ones</Description>
    <Slots>
      <Any />
    </Slots>
    <Effects>
      <Roll Bonus="0" DiceMult="1" UsesCumulativeBonus="false" TargetsUser="true" />
    </Effects>
  </AbilityData>
  <AbilityData ID="Vulnerable Spread" Uses="0" Price="0">
    <Description>Spread your legs unconsciously, showing your vulnerability and 5 _Aro</Description>
    <Slots>
      <Equals Value="3" />
    </Slots>
    <Effects>
      <Trait Bonus="5" UsesCumulativeBonus="false" TargetsUser="false" Trait="Aroused" />
    </Effects>
  </AbilityData>
  <AbilityData ID="Sleep Hug" Uses="0" Price="0">
    <Description>Grab your opponent in your sleep, for _Die _Bon</Description>
    <Slots>
      <Any />
    </Slots>
    <Effects>
      <Trait Bonus="0" DiceMult="1" UsesCumulativeBonus="false" TargetsUser="false" Trait="Bondage" />
    </Effects>
  </AbilityData>
  <AbilityData ID="Spider Kiss" Uses="0" Price="0">
    <Description>Slow kiss 1 + _++ _Aro, deeper each time</Description>
    <Slots>
      <Any />
    </Slots>
    <Effects>
      <Trait Bonus="1" UsesCumulativeBonus="true" TargetsUser="false" Trait="Aroused" />
    </Effects>
  </AbilityData>
  <AbilityData ID="Web" Uses="0" Price="0">
    <Description>Webs for 3 _Bon</Description>
    <Slots>
      <Equals Value="5" />
    </Slots>
    <Effects>
      <Trait Bonus="3" UsesCumulativeBonus="false" TargetsUser="false" Trait="Bondage" />
    </Effects>
  </AbilityData>
  <AbilityData ID="Webjob" Uses="0" Price="0">
    <Description>Rubs for _Die, adds 1_Sti and _Cha</Description>
    <Slots>
      <EvenOdd isEven="false" />
      <EvenOdd isEven="true" />
    </Slots>
    <Effects>
      <Damage Bonus="0" DiceMult="1" UsesCumulativeBonus="false" TargetsUser="false" />
      <Trait Bonus="1" UsesCumulativeBonus="false" TargetsUser="false" Trait="Sticky" />
      <Trait Bonus="1" UsesCumulativeBonus="false" TargetsUser="false" Trait="Chastity" />
    </Effects>
  </AbilityData>
  <AbilityData ID="Molest" Uses="0" Price="0">
    <Description>Roughly molest your opponent for _Die</Description>
    <Slots>
      <EvenOdd isEven="false" />
    </Slots>
    <Effects>
      <Damage Bonus="0" DiceMult="1" UsesCumulativeBonus="false" TargetsUser="false" />
    </Effects>
  </AbilityData>
  <AbilityData ID="Pump Up" Uses="0" Price="0">
    <Description>Pick two _Die and add them together, plus a small bonus</Description>
    <Slots>
      <Any />
      <Any />
    </Slots>
    <Effects>
      <Give Bonus="1" DiceMult="1" UsesCumulativeBonus="false" TargetsUser="true" />
    </Effects>
  </AbilityData>
  <AbilityData ID="Sweet Sweat" Uses="0" Price="0">
    <Description>Use your built up sweat to gain _Phe</Description>
    <Slots>
      <MinMax Value="3" IsMax="true" />
    </Slots>
    <Effects>
      <Trait Bonus="0" DiceMult="1" UsesCumulativeBonus="false" TargetsUser="true" Trait="Pheromones" />
    </Effects>
  </AbilityData>
</ArrayOfAbilityData>